README.md
requirements-dev.txt
requirements.txt
setup.py
argetype/__init__.py
argetype/pipelines.py
argetype/tasks.py
argetype/typings.py
argetype.egg-info/PKG-INFO
argetype.egg-info/SOURCES.txt
argetype.egg-info/dependency_links.txt
argetype.egg-info/not-zip-safe
argetype.egg-info/requires.txt
argetype.egg-info/top_level.txt