Metadata-Version: 2.1
Name: argetype
Version: 0.0.7
Summary: Embracing builtin python modules argparse and typing
Home-page: https://github.com/dicaso/argetype
Author: Christophe Van Neste
Author-email: christophe.vanneste@kaust.edu.sa
License: MIT
Platform: UNKNOWN
Requires-Python: >=3.6
Provides-Extra: documentation
